cdk_serverless_airflow/__init__.py
cdk_serverless_airflow/py.typed
cdk_serverless_airflow/_jsii/__init__.py
cdk_serverless_airflow/_jsii/cdk-serverless-airflow@0.7.6.jsii.tgz
cdk_serverless_airflow-0.7.6.dist-info/LICENSE
cdk_serverless_airflow-0.7.6.dist-info/METADATA
cdk_serverless_airflow-0.7.6.dist-info/WHEEL
cdk_serverless_airflow-0.7.6.dist-info/top_level.txt
cdk_serverless_airflow-0.7.6.dist-info/RECORD
