Metadata-Version: 2.1
Name: cdk-serverless-airflow
Version: 0.7.6
Summary: cdk-serverless-airflow
Home-page: https://github.com/readybuilderone/serverless-airflow.git
Author: readybuilderone<neohan2016@outlook.com>
License: Apache-2.0
Project-URL: Source, https://github.com/readybuilderone/serverless-airflow.git
Platform: UNKNOWN
Classifier: Intended Audience :: Developers
Classifier: Operating System :: OS Independent
Classifier: Programming Language :: JavaScript
Classifier: Programming Language :: Python :: 3 :: Only
Classifier: Programming Language :: Python :: 3.6
Classifier: Programming Language :: Python :: 3.7
Classifier: Programming Language :: Python :: 3.8
Classifier: Programming Language :: Python :: 3.9
Classifier: Typing :: Typed
Classifier: Development Status :: 5 - Production/Stable
Classifier: License :: OSI Approved
Requires-Python: >=3.6
License-File: LICENSE
Requires-Dist: aws-cdk.aws-ec2 (<2.0.0,>=1.95.2)
Requires-Dist: aws-cdk.aws-ecr-assets (<2.0.0,>=1.95.2)
Requires-Dist: aws-cdk.aws-ecr (<2.0.0,>=1.95.2)
Requires-Dist: aws-cdk.aws-ecs-patterns (<2.0.0,>=1.95.2)
Requires-Dist: aws-cdk.aws-ecs (<2.0.0,>=1.95.2)
Requires-Dist: aws-cdk.aws-elasticache (<2.0.0,>=1.95.2)
Requires-Dist: aws-cdk.aws-events (<2.0.0,>=1.95.2)
Requires-Dist: aws-cdk.aws-iam (<2.0.0,>=1.95.2)
Requires-Dist: aws-cdk.aws-logs (<2.0.0,>=1.95.2)
Requires-Dist: aws-cdk.aws-rds (<2.0.0,>=1.95.2)
Requires-Dist: aws-cdk.aws-s3 (<2.0.0,>=1.95.2)
Requires-Dist: aws-cdk.aws-secretsmanager (<2.0.0,>=1.95.2)
Requires-Dist: aws-cdk.aws-servicediscovery (<2.0.0,>=1.95.2)
Requires-Dist: aws-cdk.core (<2.0.0,>=1.95.2)
Requires-Dist: constructs (<4.0.0,>=3.2.27)
Requires-Dist: jsii (<2.0.0,>=1.34.0)
Requires-Dist: publication (>=0.0.3)
